<?xml version="1.0" encoding="utf-8"?>
<Defs>

	<ThingDef ParentName="BaseWeapon_Bladelink">
		<defName>VPWE_MeleeWeapon_PsyfocusStaffBladelink</defName>
		<label>persona eltex staff</label>
		<description>An ultratech staff threaded with psychic focusing materials. While it is a solid melee weapon, its main purpose is to enhance the wielder's psychic sensitivity and neural heat dissipation, allowing more use of psychic powers.
\nThis weapon has an onboard persona that can bond to only a single person. The wielder and intelligent weapon can synchronize their reflexes and attack with frightening speed, accuracy, and creativity. Once bonded to a wielder, the weapon's persona will refuse to be wielded by anyone else.</description>
		<graphicData>
			<texPath>Things/Item/Equipment/WeaponMelee/PsyfocusStaff</texPath>
			<graphicClass>Graphic_Single</graphicClass>
		</graphicData>
		<smeltable>false</smeltable>
		<techLevel>Ultra</techLevel>
		<relicChance>3</relicChance>
		<tradeTags>
			<li>PsychicWeapon</li>
		</tradeTags>
		<weaponTags>
			<li>EltexStaff</li>
		</weaponTags>
		<weaponClasses>
			<li>MeleeBlunt</li>
			<li>Ultratech</li>
		</weaponClasses>
		<statBases>
			<MarketValue>3000</MarketValue>
			<Mass>1.2</Mass>
		</statBases>
		<equippedAngleOffset>-65</equippedAngleOffset>
		<equippedStatOffsets>
			<PsychicSensitivityOffset>0.50</PsychicSensitivityOffset>
			<PsychicEntropyRecoveryRate>0.083</PsychicEntropyRecoveryRate>
		</equippedStatOffsets>
		<tools>
			<li>
				<label>head</label>
				<labelUsedInLogging>false</labelUsedInLogging>
				<capacities>
					<li>Blunt</li>
				</capacities>
				<power>12</power>
				<cooldownTime>2.6</cooldownTime>
			</li>
		</tools>
		<comps>
			<li Class="VEF.Graphics.CompProperties_GraphicCustomization">
				<compClass>VanillaPersonaWeaponsExpanded.CompGraphicCustomization_PsychicWeapon</compClass>
				<customizable>true</customizable>
				<customizationTitle>Persona Weapon Customization</customizationTitle>
				<graphics>
					<li>
						<name>Grip</name>
						<texVariants>
							<li>
								<texName>Astralite</texName>
								<outline>EltexStaff/EltexStaff_Grip_Astralite_Outline</outline>
								<texture>EltexStaff/EltexStaff_Grip_Astralite</texture>
							</li>
							<li>
								<texName>Cerebrum</texName>
								<outline>EltexStaff/EltexStaff_Grip_Cerebrum_Outline</outline>
								<texture>EltexStaff/EltexStaff_Grip_Cerebrum</texture>
							</li>
							<li>
								<texName>Etherium</texName>
								<outline>EltexStaff/EltexStaff_Grip_Etherium_Outline</outline>
								<texture>EltexStaff/EltexStaff_Grip_Etherium</texture>
							</li>
							<li>
								<texName>Ethertwine</texName>
								<outline>EltexStaff/EltexStaff_Grip_Ethertwine_Outline</outline>
								<texture>EltexStaff/EltexStaff_Grip_Ethertwine</texture>
							</li>
							<li>
								<texName>Mindrift</texName>
								<outline>EltexStaff/EltexStaff_Grip_Mindrift_Outline</outline>
								<texture>EltexStaff/EltexStaff_Grip_Mindrift</texture>
							</li>
							<li>
								<texName>Mindspire</texName>
								<outline>EltexStaff/EltexStaff_Grip_Mindspire_Outline</outline>
								<texture>EltexStaff/EltexStaff_Grip_Mindspire</texture>
							</li>
							<li>
								<texName>Neurolink</texName>
								<outline>EltexStaff/EltexStaff_Grip_Neurolink_Outline</outline>
								<texture>EltexStaff/EltexStaff_Grip_Neurolink</texture>
							</li>
							<li>
								<texName>Neuronex</texName>
								<outline>EltexStaff/EltexStaff_Grip_Neuronex_Outline</outline>
								<texture>EltexStaff/EltexStaff_Grip_Neuronex</texture>
							</li>
							<li>
								<texName>Psionite</texName>
								<outline>EltexStaff/EltexStaff_Grip_Psionite_Outline</outline>
								<texture>EltexStaff/EltexStaff_Grip_Psionite</texture>
							</li>
							<li>
								<texName>Psychomere</texName>
								<outline>EltexStaff/EltexStaff_Grip_Psychomere_Outline</outline>
								<texture>EltexStaff/EltexStaff_Grip_Psychomere</texture>
							</li>
							<li>
								<texName>Psyclasp</texName>
								<outline>EltexStaff/EltexStaff_Grip_Psyclasp_Outline</outline>
								<texture>EltexStaff/EltexStaff_Grip_Psyclasp</texture>
							</li>
							<li>
								<texName>Psycore</texName>
								<outline>EltexStaff/EltexStaff_Grip_Psycore_Outline</outline>
								<texture>EltexStaff/EltexStaff_Grip_Psycore</texture>
							</li>
							<li>
								<texName>Synaptis</texName>
								<outline>EltexStaff/EltexStaff_Grip_Synaptis_Outline</outline>
								<texture>EltexStaff/EltexStaff_Grip_Synaptis</texture>
							</li>
							<li>
								<texName>Thoughtstream</texName>
								<outline>EltexStaff/EltexStaff_Grip_Thoughtstream_Outline</outline>
								<texture>EltexStaff/EltexStaff_Grip_Thoughtstream</texture>
							</li>
							<li>
								<texName>Thoughtweave</texName>
								<outline>EltexStaff/EltexStaff_Grip_Thoughtweave_Outline</outline>
								<texture>EltexStaff/EltexStaff_Grip_Thoughtweave</texture>
							</li>
						</texVariants>
					</li>
					<li>
						<name>Head</name>
						<texVariants>
							<li>
								<texName>Brainflux</texName>
								<outline>EltexStaff/EltexStaff_Head_Brainflux_Outline</outline>
								<texture>EltexStaff/EltexStaff_Head_Brainflux</texture>
							</li>
							<li>
								<texName>Brainwave</texName>
								<outline>EltexStaff/EltexStaff_Head_Brainwave_Outline</outline>
								<texture>EltexStaff/EltexStaff_Head_Brainwave</texture>
							</li>
							<li>
								<texName>Cognisphere</texName>
								<outline>EltexStaff/EltexStaff_Head_Cognisphere_Outline</outline>
								<texture>EltexStaff/EltexStaff_Head_Cognisphere</texture>
							</li>
							<li>
								<texName>Cognitron</texName>
								<outline>EltexStaff/EltexStaff_Head_Cognitron_Outline</outline>
								<texture>EltexStaff/EltexStaff_Head_Cognitron</texture>
							</li>
							<li>
								<texName>Enigmaflux</texName>
								<outline>EltexStaff/EltexStaff_Head_Enigmaflux_Outline</outline>
								<texture>EltexStaff/EltexStaff_Head_Enigmaflux</texture>
							</li>
							<li>
								<texName>Intellectron</texName>
								<outline>EltexStaff/EltexStaff_Head_Intellectron_Outline</outline>
								<texture>EltexStaff/EltexStaff_Head_Intellectron</texture>
							</li>
							<li>
								<texName>Mindharbor</texName>
								<outline>EltexStaff/EltexStaff_Head_Mindharbor_Outline</outline>
								<texture>EltexStaff/EltexStaff_Head_Mindharbor</texture>
							</li>
							<li>
								<texName>Neurocrux</texName>
								<outline>EltexStaff/EltexStaff_Head_Neurocrux_Outline</outline>
								<texture>EltexStaff/EltexStaff_Head_Neurocrux</texture>
							</li>
							<li>
								<texName>Neuromantle</texName>
								<outline>EltexStaff/EltexStaff_Head_Neuromantle_Outline</outline>
								<texture>EltexStaff/EltexStaff_Head_Neuromantle</texture>
							</li>
							<li>
								<texName>Psionicore</texName>
								<outline>EltexStaff/EltexStaff_Head_Psionicore_Outline</outline>
								<texture>EltexStaff/EltexStaff_Head_Psionicore</texture>
							</li>
							<li>
								<texName>Psychonex</texName>
								<outline>EltexStaff/EltexStaff_Head_Psychonex_Outline</outline>
								<texture>EltexStaff/EltexStaff_Head_Psychonex</texture>
							</li>
							<li>
								<texName>Psymatrix</texName>
								<outline>EltexStaff/EltexStaff_Head_Psymatrix_Outline</outline>
								<texture>EltexStaff/EltexStaff_Head_Psymatrix</texture>
							</li>
							<li>
								<texName>Sentientium</texName>
								<outline>EltexStaff/EltexStaff_Head_Sentientium_Outline</outline>
								<texture>EltexStaff/EltexStaff_Head_Sentientium</texture>
							</li>
							<li>
								<texName>Spiritforge</texName>
								<outline>EltexStaff/EltexStaff_Head_Spiritforge_Outline</outline>
								<texture>EltexStaff/EltexStaff_Head_Spiritforge</texture>
							</li>
							<li>
								<texName>Synapsestone</texName>
								<outline>EltexStaff/EltexStaff_Head_Synapsestone_Outline</outline>
								<texture>EltexStaff/EltexStaff_Head_Synapsestone</texture>
							</li>
						</texVariants>
					</li>
					<li>
						<name>Crystal</name>
						<texVariants>
							<li>
								<texName>Aethercryst</texName>
								<outline>EltexStaff/EltexStaff_Crystal_Aethercryst_Outline</outline>
								<texture>EltexStaff/EltexStaff_Crystal_Aethercryst</texture>
							</li>
							<li>
								<texName>Astraquartz</texName>
								<outline>EltexStaff/EltexStaff_Crystal_Astraquartz_Outline</outline>
								<texture>EltexStaff/EltexStaff_Crystal_Astraquartz</texture>
							</li>
							<li>
								<texName>Cerebrastone</texName>
								<outline>EltexStaff/EltexStaff_Crystal_Cerebrastone_Outline</outline>
								<texture>EltexStaff/EltexStaff_Crystal_Cerebrastone</texture>
							</li>
							<li>
								<texName>Cerebroshard</texName>
								<outline>EltexStaff/EltexStaff_Crystal_Cerebroshard_Outline</outline>
								<texture>EltexStaff/EltexStaff_Crystal_Cerebroshard</texture>
							</li>
							<li>
								<texName>Mindcrystal</texName>
								<outline>EltexStaff/EltexStaff_Crystal_Mindcrystal_Outline</outline>
								<texture>EltexStaff/EltexStaff_Crystal_Mindcrystal</texture>
							</li>
							<li>
								<texName>Mindfacet</texName>
								<outline>EltexStaff/EltexStaff_Crystal_Mindfacet_Outline</outline>
								<texture>EltexStaff/EltexStaff_Crystal_Mindfacet</texture>
							</li>
							<li>
								<texName>Neuralite</texName>
								<outline>EltexStaff/EltexStaff_Crystal_Neuralite_Outline</outline>
								<texture>EltexStaff/EltexStaff_Crystal_Neuralite</texture>
							</li>
							<li>
								<texName>Neuromarble</texName>
								<outline>EltexStaff/EltexStaff_Crystal_Neuromarble_Outline</outline>
								<texture>EltexStaff/EltexStaff_Crystal_Neuromarble</texture>
							</li>
							<li>
								<texName>Psioncryst</texName>
								<outline>EltexStaff/EltexStaff_Crystal_Psioncryst_Outline</outline>
								<texture>EltexStaff/EltexStaff_Crystal_Psioncryst</texture>
							</li>
							<li>
								<texName>Psychgem</texName>
								<outline>EltexStaff/EltexStaff_Crystal_Psychgem_Outline</outline>
								<texture>EltexStaff/EltexStaff_Crystal_Psychgem</texture>
							</li>
							<li>
								<texName>Psychicore</texName>
								<outline>EltexStaff/EltexStaff_Crystal_Psychicore_Outline</outline>
								<texture>EltexStaff/EltexStaff_Crystal_Psychicore</texture>
							</li>
							<li>
								<texName>Psymoon</texName>
								<outline>EltexStaff/EltexStaff_Crystal_Psymoon_Outline</outline>
								<texture>EltexStaff/EltexStaff_Crystal_Psymoon</texture>
							</li>
							<li>
								<texName>Psyquartz</texName>
								<outline>EltexStaff/EltexStaff_Crystal_Psyquartz_Outline</outline>
								<texture>EltexStaff/EltexStaff_Crystal_Psyquartz</texture>
							</li>
							<li>
								<texName>Thoughtmatrix</texName>
								<outline>EltexStaff/EltexStaff_Crystal_Thoughtmatrix_Outline</outline>
								<texture>EltexStaff/EltexStaff_Crystal_Thoughtmatrix</texture>
							</li>
							<li>
								<texName>Thoughtstone</texName>
								<outline>EltexStaff/EltexStaff_Crystal_Thoughtstone_Outline</outline>
								<texture>EltexStaff/EltexStaff_Crystal_Thoughtstone</texture>
							</li>
						</texVariants>
					</li>
				</graphics>
			</li>
		</comps>
	</ThingDef>


</Defs>